ex_reminder.py
ex_reminder-1.0.dist-info/METADATA
ex_reminder-1.0.dist-info/WHEEL
ex_reminder-1.0.dist-info/top_level.txt
ex_reminder-1.0.dist-info/RECORD
